pyhubo/HuboHamiltonian.py
pyhubo/VariableAssignment.py
pyhubo/VariableDictionary.py
pyhubo/__init__.py
pyhubo-1.0.3.dist-info/METADATA
pyhubo-1.0.3.dist-info/WHEEL
pyhubo-1.0.3.dist-info/licenses/LICENSE
pyhubo-1.0.3.dist-info/RECORD
