Metadata-Version: 2.4
Name: pyhubo
Version: 1.0.3
Summary: A python package for resource-efficient quantum optimization
Project-URL: Homepage, https://github.com/frederikKoch/PyHUBO
Project-URL: Issues, https://github.com/frederikKoch/PyHUBO
Author-email: Frederik Koch <frederik.koch@uni-hamburg.de>
License-Expression: MIT
License-File: LICENSE
Classifier: Operating System :: OS Independent
Classifier: Programming Language :: Python :: 3
Requires-Python: >=3.10
